{
  "model": "RandomForest",
  "target": "Pc_MPa",
  "feature_set": "FS2",
  "params": {
    "n_estimators": 300,
    "max_features": 0.33,
    "min_samples_leaf": 2
  },
  "elapsed_s": 1.48,
  "cv_metrics": [
    {
      "rmse": 0.387968357499809,
      "mae": 0.29325207925026686,
      "mape": 7.239940192887049,
      "r2": 0.8881980102623809,
      "nrmse": 1.8300394221689105,
      "fold": 0
    },
    {
      "rmse": 1.081379716152,
      "mae": 0.5797478144169909,
      "mape": 13.627966451698226,
      "r2": 0.1432841794021752,
      "nrmse": 5.100847717698113,
      "fold": 1
    },
    {
      "rmse": 1.7632108910155513,
      "mae": 0.5322186788449746,
      "mape": 8.479778769347343,
      "r2": 0.5117793659083718,
      "nrmse": 8.317032504790337,
      "fold": 2
    },
    {
      "rmse": 0.8909506560645845,
      "mae": 0.46261902379678155,
      "mape": 13.407357398121158,
      "r2": 0.7513097976898919,
      "nrmse": 4.202597434266908,
      "fold": 3
    },
    {
      "rmse": 0.563691206439912,
      "mae": 0.3383723985373087,
      "mape": 8.758489997925949,
      "r2": 0.8538207713606663,
      "nrmse": 2.6589207850939247,
      "fold": 4
    }
  ],
  "mean_metrics": {
    "rmse": 0.9374401654343713,
    "mae": 0.4412419989692645,
    "mape": 10.302706561995944,
    "r2": 0.6296784249246972,
    "nrmse": 4.421887572803639
  },
  "std_metrics": {
    "rmse": 0.4788287192793313,
    "mae": 0.10990974971856587,
    "mape": 2.675235261206728,
    "r2": 0.27653061620880026,
    "nrmse": 2.2586260343364684
  },
  "oof_true": [
    5.906115,
    5.782645,
    4.828,
    6.929003,
    5.041692,
    5.009983,
    4.51675,
    3.761818,
    4.059276,
    3.618276,
    4.554993,
    3.517868,
    3.382245,
    3.634871,
    3.530643,
    3.623689,
    7.377298,
    11.363391,
    4.407638,
    4.136166,
    3.973109,
    5.288505,
    3.392266,
    3.352482,
    3.129171,
    3.661805,
    3.624483,
    4.211652,
    4.054783,
    4.99,
    3.650995,
    3.952545,
    2.779002,
    7.886579,
    5.336665,
    5.605283,
    3.956,
    4.015,
    5.132,
    7.244817,
    8.998872,
    6.3688,
    3.138,
    3.342,
    3.177,
    4.13,
    3.55,
    2.9,
    4.61,
    4.43,
    5.71,
    3.672,
    4.245,
    3.67,
    4.06,
    4.06,
    3.12,
    2.55,
    1.92,
    4.15,
    4.04,
    5.02,
    5.51,
    5.32,
    3.52,
    3.56,
    5.239517,
    4.46,
    4.84,
    7.16,
    5.47,
    3.796,
    3.629,
    3.367519,
    3.378217,
    3.196297,
    4.005724,
    4.236038,
    4.019095,
    3.266392,
    3.762456,
    3.04766,
    2.640206,
    2.777531,
    4.5992,
    4.8722,
    4.251165,
    3.3958,
    5.046411,
    4.863001,
    3.498195,
    5.525432,
    4.906289,
    4.126347,
    3.622442,
    3.73746,
    3.534599,
    3.531521,
    4.582766,
    4.080526,
    22.064,
    1.931134,
    1.437538,
    1.144009,
    0.953951,
    0.828559,
    1.347215,
    1.077688,
    0.961416,
    8.215853,
    6.267915,
    5.2,
    4.9,
    4.5,
    5.781,
    4.692417,
    3.8,
    4.1,
    6.138,
    5.657503,
    4.6,
    4.57,
    4.493,
    5.32868,
    6.355,
    5.24053,
    5.226121,
    6.01,
    5.36,
    4.5505,
    4.5191,
    4.52,
    3.3,
    3.79,
    3.471,
    7.304687,
    5.44,
    3.9,
    8.2,
    1.7,
    1.6,
    1.5,
    1.4,
    2.74,
    2.81,
    2.77,
    2.91,
    2.74,
    2.95,
    2.89,
    2.95,
    2.5,
    2.55,
    2.54,
    2.49,
    2.57,
    2.73,
    3.82,
    3.56,
    2.08,
    2.323,
    2.045,
    1.872,
    3.42,
    3.06,
    2.7,
    4.2,
    3.31,
    4.08,
    4.4,
    5.93,
    7.5,
    6.1,
    4.77,
    4.668,
    4.064,
    3.63,
    4.47,
    5.81,
    4.75,
    3.882,
    3.335,
    3.09,
    3.362,
    3.473,
    3.3,
    1.246001,
    1.349958,
    1.238999,
    1.340821,
    1.368997,
    4.2,
    3.729,
    3.39,
    4.6,
    4.4,
    3.694,
    5.55,
    5.14,
    4.32,
    4.65,
    5.51,
    4.87,
    4.26,
    4.215,
    4.66,
    3.028,
    3.01,
    5.19,
    5.47155,
    4.2,
    3.397,
    5.65,
    5.53,
    5.7,
    7.23,
    3.96,
    3.21,
    3.13,
    3.1,
    3.95,
    3.7,
    3.38,
    3.6,
    4.57786,
    4.75,
    3.97,
    3.95,
    3.35,
    4.65,
    4.6,
    4.3,
    4.48,
    4.798,
    4.36,
    4.05,
    6.23149,
    5.67,
    5.87,
    5.17,
    5.11,
    7.75,
    6.51,
    2.9,
    2.9,
    2.9,
    3.63,
    4.5,
    3.8,
    2.67,
    3.09,
    4.0,
    3.6,
    4.14,
    3.27,
    3.167,
    3.16,
    3.339,
    3.72,
    1.869027,
    3.2,
    3.45,
    2.89,
    3.05,
    2.58,
    5.02,
    4.9,
    4.14,
    3.86,
    2.0,
    2.019,
    6.21,
    6.22,
    6.04,
    5.42,
    4.0,
    6.004,
    4.738,
    4.004,
    3.29,
    3.01,
    4.5,
    3.94,
    3.93,
    3.97,
    4.96,
    6.91,
    5.17,
    3.44,
    3.22,
    3.352,
    4.6,
    3.77,
    3.8,
    4.59,
    2.78,
    2.55,
    3.24,
    4.26,
    3.11,
    3.6,
    5.78,
    5.07,
    5.28,
    5.28,
    4.44,
    4.3,
    3.35,
    5.07,
    3.75,
    3.34,
    5.42,
    1.61,
    1.52,
    2.4,
    3.3,
    3.2,
    6.4,
    5.67,
    5.16,
    5.67,
    2.63,
    2.6,
    3.31,
    3.87,
    3.71,
    4.9,
    4.06,
    3.36,
    3.07,
    3.16,
    2.85,
    2.09,
    3.64,
    4.77,
    5.11,
    2.8,
    2.76,
    2.8,
    2.6,
    2.8,
    3.43,
    5.92,
    5.13,
    1.75,
    2.0,
    1.67,
    10.13,
    6.48,
    10.1,
    2.73,
    2.74,
    2.61,
    2.63,
    2.56,
    2.69,
    2.74,
    2.48,
    4.26,
    3.77,
    3.68,
    4.185,
    3.98,
    3.04,
    3.59,
    4.07,
    3.98,
    4.07,
    3.87,
    4.05,
    4.64,
    4.72,
    3.75763,
    3.13,
    6.48,
    3.26,
    4.25,
    2.89,
    3.63,
    2.57,
    2.5,
    4.0,
    4.6,
    3.7,
    4.1,
    4.73,
    3.67
  ],
  "oof_pred": [
    5.8291386235899445,
    5.667386552527779,
    4.855051397174604,
    5.826008804304228,
    5.810642440555556,
    5.601040310726189,
    5.049909658366405,
    4.33369385022751,
    3.9998724640978844,
    3.477981666232804,
    5.102164644384914,
    3.9684625020436513,
    3.5314489591507914,
    3.5694689592539657,
    3.6066123362460294,
    3.586638775103172,
    6.95423402367858,
    11.212206237550268,
    4.322881490039682,
    4.15177044980291,
    4.131699985735448,
    4.918033616588624,
    3.355179278939154,
    3.2911914951666663,
    3.1812720864285713,
    3.612958163738096,
    3.5355302447883603,
    4.245324516410054,
    4.120040015843911,
    4.81977004001323,
    3.3313322953862428,
    4.086259013076719,
    3.142578613507938,
    6.533535376764548,
    5.759376761976187,
    4.626549220083337,
    4.184283185354495,
    4.4407943667989445,
    5.091568984503965,
    7.613783815549666,
    6.601462832909215,
    6.391161736324672,
    3.4380436770389595,
    3.435233592779701,
    3.1598238827010574,
    4.331831058708993,
    3.592019078125659,
    3.191500162888889,
    4.098376892480158,
    5.080195552160054,
    5.741206531888887,
    3.9411814944550256,
    4.3829926053057955,
    3.6584128183968248,
    3.907632707828522,
    4.527727116129628,
    3.0595448926957682,
    2.2902181834497335,
    2.3272746039179886,
    4.429310646806039,
    4.227341408693605,
    4.580544070000001,
    5.132981000759263,
    5.1439689286798975,
    3.5740702853558197,
    3.312350182218255,
    4.860871461992065,
    5.11322987571032,
    6.7739760986349165,
    5.608651301256611,
    4.996551587855702,
    4.225540214638884,
    4.397511255535711,
    3.892928384123016,
    3.8806414312896824,
    4.090132248392857,
    4.457532374460317,
    4.3968569380806874,
    4.388680217144179,
    3.335433497105819,
    4.211593064226191,
    3.332695325993385,
    2.8865902303320086,
    2.9476347275555552,
    7.692664054558201,
    5.4846960344642826,
    4.9859850623664,
    7.981421911626978,
    7.385708353460309,
    7.459790541627828,
    6.931253924138887,
    7.473175679238938,
    4.5089203335341494,
    4.029003993894178,
    3.769616185015873,
    3.8183497513425912,
    3.78721020412037,
    3.7595916825727524,
    4.201384353682423,
    3.890389677253127,
    7.355159286984611,
    2.8772653880194823,
    2.3706778898677263,
    1.73677229239947,
    1.6077183595767186,
    1.5222524211560844,
    1.9299748965502648,
    1.73433560118783,
    1.6543287746005284,
    7.328100638251314,
    6.086533360547619,
    5.098427173190479,
    5.098065246948416,
    4.34155625026768,
    6.148140884997352,
    5.119852313235449,
    4.092350339485448,
    3.9665928002142854,
    6.097219844023808,
    5.219992879357146,
    4.655846295440477,
    4.753117386071424,
    4.2162120508015875,
    4.839598615706353,
    5.679726985382275,
    5.543669222083335,
    4.943250812124335,
    5.85403411133598,
    5.737571497211643,
    4.815352593859793,
    4.352760826891776,
    4.270895306518764,
    3.13565221603704,
    3.820772058515873,
    3.6459971266774893,
    5.565633585383598,
    4.975198035590662,
    3.950566034835017,
    6.3654486044642855,
    2.1598037143928583,
    1.7687271173505272,
    1.7076133312552904,
    1.6480190894775126,
    2.9910719080833346,
    3.0248141119722223,
    3.017912439130953,
    2.999283379480158,
    2.996032178170635,
    3.0297936752658723,
    3.043632464305555,
    3.053690756316137,
    2.6287423697777785,
    2.6302567661349223,
    2.643635375158733,
    2.631124311984128,
    2.691317345746034,
    2.7155475524127004,
    3.7156971117063486,
    3.3967315123439157,
    2.9907283330634917,
    2.401001033956349,
    2.1771331327023815,
    1.9767274962698407,
    3.3250892812698383,
    3.1602548678783067,
    3.01802962989418,
    4.3838283176204955,
    3.339015476277775,
    4.172690009296298,
    4.405372400873013,
    4.870395643137569,
    5.846471993414618,
    5.983783256257935,
    4.341632438311447,
    5.271112238338628,
    4.490341061558196,
    3.657578518391531,
    4.567186411822749,
    7.794131015447092,
    4.774957058429899,
    4.173456527269844,
    3.48487145356614,
    3.231187803587302,
    3.5536501490317467,
    3.5631288410158746,
    3.3794259887287175,
    1.3529415265158724,
    1.3909185690634915,
    1.351025052968253,
    1.3543299256111103,
    1.3795073499603163,
    4.487966223452384,
    4.030252914238094,
    3.395571507542327,
    4.238202017682537,
    4.057163226722224,
    4.001801881603177,
    6.0160651606269875,
    4.864240987603174,
    4.3915269282724925,
    4.465754673214282,
    4.844440059857141,
    6.235649210820111,
    4.971323345683862,
    4.509897624187826,
    5.265343309731484,
    3.4197456459285687,
    2.901273913746993,
    4.73897710052116,
    4.7435192617129625,
    4.3182780170793675,
    3.8255952148042365,
    5.259341054182538,
    5.446955747304952,
    4.944355301841029,
    5.815753574715008,
    3.965011817810248,
    3.240827216732804,
    3.3036400579523826,
    3.330747765341271,
    4.1503185451604105,
    3.6302808460476204,
    2.9932638906772473,
    3.2533679879894186,
    4.575418522465614,
    4.705888029529105,
    4.0326550036613735,
    4.034210066158727,
    3.6583806663240783,
    4.297201125010582,
    4.3098419527169325,
    4.318494373765873,
    4.38418389651455,
    4.488712480892857,
    4.605506395242062,
    3.944885348470898,
    5.219758375083333,
    5.990248846248679,
    6.198241674052311,
    5.022453799456351,
    5.126276721871695,
    7.446545886501322,
    6.431318268321428,
    3.0600631880687876,
    3.0537014797354547,
    3.358315335150796,
    3.7916552109629675,
    4.978093232896828,
    4.4190775451746065,
    3.4139465501005293,
    3.7229751886322733,
    5.1180850223862455,
    3.597122587113757,
    4.7488247663196255,
    3.2683397320714294,
    3.549576149665946,
    3.6740373612331694,
    3.6867727236220587,
    3.974851476380953,
    2.010081566231601,
    3.204589666439152,
    3.2093614012116403,
    3.038912219632272,
    3.090606534473541,
    2.6552587628015893,
    5.1500809799126985,
    4.581800259055559,
    4.551227730626986,
    4.023085010650797,
    1.9806088496031744,
    2.0345510389444446,
    5.812810051646825,
    4.851883101137567,
    4.599011784896829,
    5.459530735809526,
    4.430993595857141,
    6.015888999410059,
    5.089937316195769,
    4.189985204148144,
    3.442341998595235,
    3.2803628629722215,
    4.393292290492067,
    3.9954029500453347,
    3.942715207001683,
    4.35670961652381,
    4.417253265452379,
    5.2954616566044965,
    4.774592722695768,
    3.250958770343915,
    3.2860264788809546,
    3.255657665349206,
    4.555731966984126,
    3.2075324837962964,
    3.490502153698416,
    3.953650311653439,
    2.963907641055555,
    2.393049472415344,
    3.2721999944761913,
    4.451195730290047,
    2.827634081214285,
    4.159182516729198,
    4.229983765343912,
    4.202154212621691,
    4.992672973638891,
    5.041911137440477,
    4.167244391388891,
    3.619668696142856,
    3.139427875333333,
    4.922274557559524,
    3.906365598375662,
    2.712250689007936,
    5.035121683472222,
    1.723367820718254,
    1.3999845557738104,
    2.9427311604060873,
    3.913689986208997,
    2.8090037077380927,
    3.8296999487857146,
    5.39749821334127,
    5.1379047724682545,
    5.8631675826534435,
    2.6269601295714273,
    2.2688338117539684,
    3.2560822016378053,
    3.858508570825883,
    3.8032160357566167,
    4.717911584571424,
    3.8723757043083205,
    3.3238475056226546,
    2.7878028027549306,
    3.2842358102539677,
    2.6931507003227524,
    2.747838918341269,
    3.573724670960318,
    4.3998885941875905,
    5.429338854976665,
    3.0179274889127,
    3.192887441679895,
    3.2274982223571422,
    2.9799245021005305,
    2.8202663759947084,
    4.397980947603173,
    5.894322856917992,
    4.741190349730161,
    1.889118097944444,
    2.0042856310317463,
    1.938621881777777,
    5.905792587914023,
    6.410578048944444,
    5.302724017322752,
    2.626133996095239,
    2.6833805337500003,
    2.562410975264549,
    2.553834804074072,
    2.548671746851849,
    2.5572685957407395,
    2.5869152498835977,
    2.5513952280317445,
    4.659785652841272,
    3.878801629044972,
    3.8190593095687806,
    4.5755305474709,
    3.8206262540873,
    3.4121069733809537,
    3.793338453425925,
    4.072615618555556,
    4.097418704034391,
    4.017991375915344,
    3.326853277697331,
    3.400190017352092,
    4.872062068830445,
    4.927466824896826,
    4.547178051126981,
    3.4489338683807085,
    11.231543804494239,
    3.980353867124338,
    3.8599716618878053,
    3.353102688939156,
    3.4744346910238066,
    2.6358544102380943,
    2.0809600855476194,
    4.539550250928571,
    5.328559200192879,
    3.3261666567698427,
    3.991748433810848,
    4.7580193342023795,
    3.5252983986230206
  ]
}